Workbook

Sheet Details MC 
A1: Collection of Maintainance Charge (Tower-II) (Flat wise)-2025/26
F3: 2BHK Rs. 1200 & 3 BHK Rs.1200 w.e.f April 2025 | J3: 2BHK Rs. 1000 & 3 BHK Rs.1200 w.e.f June 2025 | R3: 2BHK Rs. 1200 & 3 BHK Rs.1500 w.e.f 0ctober 2025
A4: 1st Floor | F4: 45748 | H4: 45778 | J4: 45809 | L4: 45839 | N4: 45870 | P4: 45901 | R4: 45931 | T4: 45962 | V4: 45992 | X4: 46023 | Z4: 46054 | AB4: 46082 | AD4: 46113 | AF4: 46143
A5: Sl. No. | B5: Name | C5: Flat No. | D5: Room Type | E5: Mobile No. | F5: Amount | G5: Date | H5: Amount | I5: Date | J5: Amount | K5: Date | L5: Amount | M5: Date | N5: Amount | O5: Date | P5: Amount | Q5: Date | R5: Amount | S5: Date | T5: Amount | U5: Date | V5: Amount | W5: Date | X5: Amount | Y5: Date | Z5: Amount | AA5: Date | AB5: Amount | AC5: Date | AD5: Amount | AE5: Date | AF5: Amount | AG5: Date | AH5: REMARKS
A6: 1 | B6: Sishir Singha | C6: 1A | D6: 3 | E6: 9609688683 | F6: 1200 | G6: 45792 | H6: 1200 | I6: 45823 | J6: 1300 | K6: 45853 | L6: 1300 | M6: 45884 | N6: 1300 | O6: 45915 | P6: 1300 | Q6: 45945 | R6: 1500 | T6: 1500 | V6: 1500 | X6: 1500 | Z6: 1500 | AB6: 1500 | AD6: 1500 | AF6: 1500
A7: 2 | B7: Mrinmoy Choudhuri | C7: 1B | D7: 3 | E7: 7557076444 | F7: 1200 | G7: 45792 | H7: 1200 | I7: 45823 | J7: 1300 | K7: 45853 | L7: 1300 | M7: 45884 | N7: 1300 | O7: 45915 | P7: 1300 | Q7: 45945 | R7: 1300 | T7: 1300 | V7: 1300 | X7: 1300 | Z7: 1500 | AB7: 1500 | AD7: 1500 | AF7: 1500
A8: 3 | B8: Nibedita Uppadhyay | C8: 1C | D8: 2 | E8: 8001604274 | F8: 1200 | G8: 45792 | H8: 1200 | I8: 45823 | J8: 1000 | K8: 45853 | L8: 1000 | M8: 45884 | N8: 1000 | O8: 45915 | P8: 1000 | Q8: 45945 | R8: 1200 | T8: 1200 | V8: 1200 | X8: 1200 | Z8: 1200 | AB8: 1200 | AD8: 1200
A9: 4 | B9: Deepsikha Office | C9: 1D | D9: 2 | F9: 1200 | G9: 45792 | H9: 1200 | I9: 45823 | J9: 1000 | K9: 45853 | L9: =1000+17200 -> 18200 | M9: 45884 | N9: 1000 | O9: 45915 | P9: 1000 | Q9: 45945 | R9: 1200 | T9: 1200 | V9: 1200
A10: 5 | B10: Arup Kr. Bandapadhya | C10: 1E | D10: 3 | E10: 9434115212 | F10: 1200 | G10: 45792 | H10: 1200 | I10: 45823 | J10: 1300 | K10: 45853 | L10: 1300 | M10: 45884 | N10: 1300 | O10: 45915 | P10: 1300 | Q10: 45945 | R10: 1500 | T10: 1500 | V10: 1500 | X10: 1500 | Z10: 1500 | AB10: 1500 | AD10: 1500 | AF10: 1500
A11: 6 | B11: Dr. Rajkumar Sangiri | C11: 1F+1H | D11: 2+3 | E11: 9474561244 | F11: 2400 | G11: 45792 | H11: 2400 | I11: 45823 | J11: 2300 | K11: 45853 | L11: 2300 | M11: 45884 | N11: 2300 | O11: 45915 | P11: 2300 | Q11: 45945 | R11: =1500+1200 -> 2700 | T11: =1500+1200 -> 2700 | V11: =1500+1200 -> 2700 | X11: =1500+1200 -> 2700 | Z11: =1500+1200 -> 2700 | AB11: =1500+1200 -> 2700 | AD11: =1500+1200 -> 2700 | AF11: =1500+1200 -> 2700
A12: 7 | B12: Sourav Kundu | C12: 1G | D12: 2 | E12: 9475044158 | F12: 1200 | G12: 45792 | H12: 1200 | I12: 45823 | J12: 1000 | K12: 45853 | L12: 1000 | M12: 45884 | N12: 1000 | O12: 45915 | P12: 1000 | Q12: 45945 | R12: 1200 | T12: 1200 | V12: 1200 | X12: 1200 | Z12: 1200 | AB12: 1200 | AD12: 1200 | AF12: 1200
A13: 2nd Floor
A14: 8 | B14: Dr. Narendranath Pal | C14: 2A+2C | D14: 2+3 | E14: 9933111420 | F14: 2400 | G14: 45792 | H14: 2400 | I14: 45823 | J14: 2300 | K14: 45853 | L14: 2300 | M14: 45884 | N14: 2300 | O14: 45915 | P14: 2300 | Q14: 45945 | R14: =1500+1200 -> 2700 | T14: =1500+1200 -> 2700 | V14: =1500+1200 -> 2700 | X14: =1500+1200 -> 2700 | Z14: =1500+1200 -> 2700 | AB14: =1500+1200 -> 2700 | AD14: =1500+1200 -> 2700 | AF14: =1500+1200 -> 2700
A15: 9 | B15: Rahul Kundu | C15: 2B | D15: 3 | E15: 9427221065 | F15: 1200 | G15: 45792 | H15: 1200 | I15: 45823 | J15: 1300 | K15: 45853 | L15: 1300 | M15: 45884 | N15: 1300 | O15: 45915 | P15: 1300 | Q15: 45945 | R15: 1500 | S15: 45915 | T15: 1500 | V15: 1500 | X15: 1500 | Z15: 1500 | AB15: 1500 | AD15: 1500 | AF15: 1500
A16: 10 | C16: 2D
A17: 11 | B17: Manju Khan | C17: 2E | D17: 3 | E17: 8962744280 | F17: 1200 | G17: 45792 | H17: 1200 | I17: 45823 | J17: 1300 | K17: 45853 | L17: 1300 | M17: 45884 | N17: 1300 | O17: 45915 | P17: 1300 | Q17: 45945 | R17: 1500 | T17: 1500 | V17: 1500 | X17: 1500 | Z17: 1500 | AB17: 1500 | AD17: 1500 | AF17: 1500
A18: 12 | B18: Madhusudan Dutta | C18: 2F | D18: 3 | E18: 9749543529 | F18: 1200 | G18: 45792 | H18: 1200 | I18: 45823 | J18: 1300 | K18: 45853 | L18: 1300 | M18: 45884 | N18: 1300 | O18: 45915 | P18: 1300 | Q18: 45945 | R18: 1500 | T18: 1500 | V18: 1500 | X18: 1500 | Z18: 1500 | AB18: 1500 | AD18: 1500 | AF18: 1500
A19: 13 | B19: Amrita Patranabish | C19: 2G | D19: 2 | E19: 7001420328 | F19: 1200 | G19: 45792 | H19: 1200 | I19: 45823 | J19: 1000 | K19: 45853 | L19: 1000 | M19: 45884 | N19: 1000 | O19: 45915 | P19: 1000 | Q19: 45945 | R19: 1200 | S19: 45938 | T19: 1200 | V19: 1200 | X19: 1200 | Z19: 1200 | AB19: 1200 | AD19: 1200 | AF19: 1200
A20: 14 | C20: 2H
A21: 3rd Floor
A22: 15 | B22: Banashree Mishra | C22: 3A | D22: 3 | E22: 8918008545 | F22: 1200 | G22: 45792 | H22: 1200 | I22: 45823 | J22: 1300 | K22: 45853 | L22: 1300 | M22: 45884 | N22: 1300 | O22: 45915 | P22: 1300 | Q22: 45945 | R22: 1500 | T22: 1500 | V22: 1500 | X22: 1500 | Z22: 1500 | AB22: 1500 | AD22: 1500 | AF22: 1500
A23: 16 | B23: Sudipta Sankar Saren | C23: 3B | D23: 3 | E23: 8967856644 | F23: 1200 | G23: 45792 | H23: 1200 | I23: 45823 | J23: 1300 | K23: 45853 | L23: 1300 | M23: 45884 | N23: 1300 | O23: 45915 | P23: 1300 | Q23: 45945 | R23: 1500 | T23: 1500 | V23: 1500 | X23: 1500 | Z23: 1500 | AB23: 1500 | AD23: 1500 | AF23: 1500
A24: 17 | B24: Paresh Das | C24: 3C | D24: 2 | E24: 8436193278 | F24: 1200 | G24: 45792 | H24: 1200 | I24: 45823 | J24: 1000 | K24: 45853 | L24: 1000 | M24: 45884 | N24: 1000 | O24: 45915 | P24: 1000 | Q24: 45945 | R24: 1200 | T24: 1200 | V24: 1200 | X24: 1200 | Z24: 1200 | AB24: 1200 | AD24: 1200 | AF24: 1200
A25: 18 | C25: 3D
A26: 19 | C26: 3E
A27: 20 | B27: Haimanti Goswami | C27: 3F | D27: 3 | E27: 9474039781 | F27: 1200 | G27: 45792 | H27: 1200 | I27: 45823 | J27: 1300 | K27: 45853 | L27: 1300 | M27: 45884 | N27: 1300 | O27: 45915 | P27: 1300 | Q27: 45945 | R27: 1500 | T27: 1500 | V27: 1500 | X27: 1500 | Z27: 1500 | AB27: 1500 | AD27: 1500 | AF27: 1500
A28: 21 | B28: Sajal Kr. Benarjee | C28: 3G | D28: 2 | E28: 8789747535 | F28: 1200 | G28: 45792 | H28: 1200 | I28: 45823 | J28: 1000 | K28: 45853 | L28: 1000 | M28: 45884 | N28: 1000 | O28: 45915 | P28: 1000 | Q28: 45945 | R28: 1200 | T28: 1200 | V28: 1200 | X28: 1200 | Z28: 1200 | AB28: 1200 | AD28: 1200 | AF28: 1200
A29: 22 | B29: Bulti Dey | C29: 3H | D29: 2 | E29: 9732006006 | F29: 1200 | G29: 45792 | H29: 1200 | I29: 45823 | J29: 1000 | K29: 45853 | L29: 1000 | M29: 45884 | N29: 1000 | O29: 45915 | P29: 1000 | Q29: 45945 | R29: 1200 | T29: 1200 | V29: 1200 | X29: 1200 | Z29: 1200 | AB29: 1200 | AD29: 1200 | AF29: 1200
A30: 4th Floor
A31: 23 | B31: Mrinmoy Mandal | C31: 4A | D31: 3 | E31: 8927777001 | F31: 1200 | G31: 45792 | H31: 1200 | I31: 45823 | J31: 1300 | K31: 45853 | L31: 1300 | M31: 45884 | N31: 1300 | O31: 45915 | P31: 1300 | Q31: 45945 | R31: 1500 | T31: 1500 | V31: 1500 | X31: 1500 | Z31: 1500 | AB31: 1500 | AD31: 1500 | AF31: 1500
A32: 24 | B32: Dr. Ajit Kr. Ganguli | C32: 4B | D32: 3 | E32: 7858953308 9835066060 | F32: 1200 | G32: 45792 | H32: 1200 | I32: 45823 | J32: 1300 | K32: 45853 | L32: 1300 | M32: 45884 | N32: 1300 | O32: 45915 | P32: 1300 | Q32: 45945 | R32: 1500 | T32: 1500 | V32: 1500 | X32: 1500 | Z32: 1500 | AB32: 1500 | AD32: 1500 | AF32: 1500
A33: 25 | B33: Ardhendu Sinha Mahapatra | C33: 4C | D33: 2 | E33: 9775033283 | F33: 1200 | G33: 45792 | H33: 1200 | I33: 45823 | J33: 1000 | K33: 45853 | L33: 1000 | M33: 45884 | N33: 1000 | O33: 45915 | P33: 1000 | Q33: 45945 | R33: 1200 | T33: 1200 | V33: 1200 | X33: 1200 | Z33: 1200 | AB33: 1200 | AD33: 1200 | AF33: 1200
A34: 26 | C34: 4D
A35: 27 | B35: Asmita Batabal | C35: 4E | D35: 3 | E35: 9007993440 | F35: 1200 | G35: 45792 | H35: 1200 | I35: 45823 | J35: 1300 | K35: 45853 | L35: 1300 | M35: 45884 | N35: 1300 | O35: 45915 | P35: 1300 | Q35: 45945 | R35: 1500 | T35: 1500 | V35: 1500 | X35: 1500 | Z35: 1500 | AB35: 1500 | AD35: 1500 | AF35: 1500
A36: 28 | B36: Deepa Haldar | C36: 4F | D36: 3 | E36: 9851121248 | F36: 1200 | G36: 45792 | H36: 1200 | I36: 45823 | J36: 1300 | K36: 45853 | L36: 1300 | M36: 45884 | N36: 1300 | O36: 45915 | P36: 1300 | Q36: 45945 | R36: 1500 | T36: 1500 | V36: 1500 | X36: 1500 | Z36: 1500 | AB36: 1500 | AD36: 1500 | AF36: 1500
A37: 29 | B37: Goutam Karmakar | C37: 4G | D37: 2 | E37: 7908578532 | F37: 1200 | G37: 45792 | H37: 1200 | I37: 45823 | J37: 1000 | K37: 45853 | L37: 1000 | M37: 45884 | N37: 1000 | O37: 45915 | P37: 1000 | Q37: 45945 | R37: 1200 | T37: 1200 | V37: 1200 | X37: 1200 | Z37: 1200 | AB37: 1200 | AD37: 1200 | AF37: 1200
A38: 30 | B38: Diptendu Mohanty | C38: 4H | D38: 2 | E38: 8637853169 | F38: 1200 | G38: 45792 | H38: 1200 | I38: 45823 | J38: 1000 | K38: 45853 | L38: 1000 | M38: 45884 | N38: 1000 | O38: 45915 | P38: 1000 | Q38: 45945 | R38: 1200 | T38: 1200 | V38: 1200 | X38: 1200 | Z38: 1200 | AB38: 1200 | AD38: 1200 | AF38: 1200
A39: 5th Floor
A40: 31 | B40: Susanta Kr. Sheet | C40: 5A | D40: 3 | E40: 9434101485 | F40: 1200 | G40: 45792 | H40: 1200 | I40: 45823 | J40: 1300 | K40: 45853 | L40: 1300 | M40: 45884 | N40: 1300 | O40: 45915 | P40: 1300 | Q40: 45945 | R40: 1500 | T40: 1500 | V40: 1500 | X40: 1500 | Z40: 1500 | AB40: 1500 | AD40: 1500 | AF40: 1500
A41: 32 | B41: Soumen Patra | C41: 5B | D41: 3 | E41: 8820411025 | F41: Registration on 30/6/25 | N41: 1300 | P41: 1300 | R41: 1500 | T41: 1500 | V41: 1500 | X41: 1500 | Z41: 1500 | AB41: 1500 | AD41: 1500 | AF41: 1500
A42: 33 | B42: Ujjal Roy | C42: 5C | D42: 2 | E42: 9749449845 | F42: 1200 | G42: 45792 | H42: 1200 | I42: 45823 | J42: 1000 | K42: 45853 | L42: 1000 | M42: 45884 | N42: 1000 | O42: 45915 | P42: 1000 | Q42: 45945 | R42: 1200 | T42: 1200 | V42: 1200 | X42: 1200 | Z42: 1200 | AB42: 1200 | AD42: 1200 | AF42: 1200
A43: 34 | B43: Krishna Sinha | C43: 5D | D43: 2 | E43: 9735135784 | F43: 1200 | G43: 45792 | H43: 1200 | I43: 45823 | J43: 1000 | K43: 45853 | L43: 1000 | M43: 45884 | N43: 1000 | O43: 45915 | P43: 1000 | Q43: 45945 | R43: 1200 | T43: 1200 | V43: 1200 | X43: 1200 | Z43: 1200 | AB43: 1200 | AD43: 1200 | AF43: 1200
A44: 35 | B44: Anita Lo Saha | C44: 5E+5G | D44: 3+2 | E44: 9474567580 | F44: 2400 | G44: 45792 | H44: 2400 | I44: 45823 | J44: 2300 | K44: 45853 | L44: 2300 | M44: 45884 | N44: 2300 | O44: 45915 | P44: 2300 | Q44: 45945 | R44: 2700 | T44: 2700 | V44: 2700 | X44: 2700 | Z44: 2700 | AB44: 2700 | AD44: 2700 | AF44: 2700
A45: 36 | B45: Sangita Roy | C45: 5F | D45: 3 | E45: 9836087162 | F45: 1200 | G45: 45792 | H45: 1200 | I45: 45823 | J45: 1300 | K45: 45853 | L45: 1300 | M45: 45884 | N45: 1300 | O45: 45915 | P45: 1300 | Q45: 45945 | R45: 1500 | T45: 1500 | V45: 1500 | X45: 1500 | Z45: 1500 | AB45: 1500 | AD45: 1500 | AF45: 1500
A46: 37 | B46: Sudipta Das | C46: 5H | D46: 2 | E46: 8101850717 | F46: 1200 | G46: 45792 | H46: 1200 | I46: 45823 | J46: 1000 | K46: 45853 | L46: 1000 | M46: 45884 | N46: 1000 | O46: 45915 | P46: 1000 | Q46: 45945 | R46: 1200 | T46: 1200 | V46: 1200 | X46: 1200 | Z46: 1200 | AB46: 1200 | AD46: 1200 | AF46: 1200
A47: 6th Floor | M47: 45884
A48: 38 | B48: Sanjay Sengupta | C48: 6A | D48: 3 | E48: 8318151358 | F48: 1200 | G48: 45792 | H48: 1200 | I48: 45823 | J48: 1300 | K48: 45853 | L48: 1300 | M48: 45884 | N48: 1300 | O48: 45915 | P48: 1300 | Q48: 45945 | R48: 1500 | T48: 1500 | V48: 1500 | X48: 1500 | Z48: 1500 | AB48: 1500 | AD48: 1500 | AF48: 1500
A49: 39 | B49: Jhuma Mandal | C49: 6B | D49: 3 | E49: 6296936814 | F49: 1200 | G49: 45792 | H49: 1200 | I49: 45823 | J49: 1300 | K49: 45853 | L49: 1300 | M49: 45884 | N49: 1300 | O49: 45915 | P49: 1300 | Q49: 45945 | R49: 1500 | T49: 1500 | V49: 1500 | X49: 1500 | Z49: 1500 | AB49: 1500 | AD49: 1500 | AF49: 1500
A50: 40 | B50: Shantanu Ganguli | C50: 6C | D50: 2 | E50: 9531571901 | F50: 1200 | G50: 45792 | H50: 1200 | I50: 45823 | J50: 1000 | K50: 45853 | L50: 1000 | M50: 45884 | N50: 1000 | O50: 45915 | P50: 1000 | Q50: 45945 | R50: 1200 | T50: 1200 | V50: 1200 | X50: 1200 | Z50: 1200 | AB50: 1200 | AD50: 1200 | AF50: 1200
A51: 41 | C51: 6D
A52: 42 | B52: Sutapa Dana | C52: 6E | D52: 3 | E52: 7680914260 | F52: 1200 | G52: 45792 | H52: 1200 | I52: 45823 | J52: 1300 | K52: 45853 | L52: 1300 | M52: 45884 | N52: 1300 | O52: 45915 | P52: 1300 | Q52: 45945 | R52: 1500 | T52: 1500 | V52: 1500 | X52: 1500 | Z52: 1500 | AB52: 1500 | AD52: 1500 | AF52: 1500
A53: 43 | B53: Deb Kumar Mondal | C53: 6F | D53: 3 | E53: 7044376634 | F53: Registration on 30/6/25 | N53: 1300 | O53: 45996 | P53: 1300 | Q53: 45996 | R53: 1500 | S53: 45996 | T53: 1500 | U53: 45996 | V53: 1500 | W53: 45996 | X53: 1500 | Z53: 1500 | AB53: 1500 | AD53: 1500 | AF53: 1500
A54: 44 | B54: Nabin Chandra Das | C54: 6G | D54: 2 | E54: 7908550094 | F54: Registration on 30/6/25 | N54: 1000 | O54: S G | P54: 1000 | Q54: S G | R54: 1200 | S54: S G | T54: 1200 | U54: S G | V54: 1200 | W54: S G | X54: 1200 | Y54: S G | Z54: 1200 | AB54: 1200 | AD54: 1200 | AF54: 1200
A55: 45 | C55: 6H | D55: 2
A56: 7th Floor
A57: 46 | B57: Dr. Arup Guha | C57: 7A | D57: 3 | E57: 7908182143 | F57: 1200 | G57: 45792 | H57: 1200 | I57: 45823 | J57: 1300 | K57: 45938 | L57: 1300 | M57: 45938 | N57: 1300 | O57: 45938 | P57: 1300 | Q57: 45938 | R57: 1500 | S57: 45938 | T57: 1500 | V57: 1500 | X57: 1500 | Z57: 1500 | AB57: 1500 | AD57: 1500 | AF57: 1500
A58: 47 | B58: Manoj Kr. Dutta | C58: 7B | D58: 3 | E58: 9933918646 | F58: 1200 | G58: 45792 | H58: 1200 | I58: 45823 | J58: 1300 | K58: 45853 | L58: 1300 | M58: 45884 | N58: 1300 | O58: 45915 | P58: 1300 | Q58: 45945 | R58: 1500 | T58: 1500
A59: 48 | B59: Shrabanti Sil Dhalla | C59: 7C | E59: 9831313288 | F59: Registration on 14/8/25 | R59: 1200 | T59: 1200 | V59: 1200 | X59: 1200 | Z59: 1200 | AB59: 1200 | AD59: 1200 | AF59: 1200
A60: 49 | C60: 7D
A61: 50 | B61: Sabir Ahammed | C61: 7E | D61: 3 | E61: 9681710268 | F61: 1200 | G61: 45792 | H61: 1200 | I61: 45823 | J61: 1300 | K61: 45853 | L61: 1300 | M61: 45884 | N61: 1300 | O61: 45915 | P61: 1300 | Q61: 45945 | R61: 1500 | T61: 1500 | V61: 1500 | X61: 1500 | Z61: 1500 | AB61: 1500 | AD61: 1500 | AF61: 1500
A62: 51 | B62: Debasish Paramanik | C62: 7F | D62: 3 | E62: 9434216284 | F62: 1200 | G62: 45792 | H62: 1200 | I62: 45823 | J62: 1300 | K62: 45853 | L62: 1300 | M62: 45884 | N62: 1300 | O62: 45915 | P62: 1300 | Q62: 45945 | R62: 1500 | T62: 1500 | V62: 1500 | X62: 1500 | Z62: 1500 | AB62: 1500 | AD62: 1500 | AF62: 1500
A63: 52 | B63: Priyanka Bandopadhyaya | C63: 7G | D63: 2 | E63: 9458208175 | F63: 1200 | G63: 45792 | H63: 1200 | I63: 45823 | J63: 1000 | K63: 45853 | L63: 1000 | M63: 45884 | N63: 1000 | O63: 45915 | P63: 1000 | Q63: 45945 | R63: 1200 | T63: 1200 | V63: 1200 | X63: 1200 | Z63: 1200 | AB63: 1200 | AD63: 1200 | AF63: 1200
A64: 53 | C64: 7H
A65: 8th Floor
A66: 54 | C66: 8A
A67: 55 | C67: 8B
A68: 56 | C68: 8C
A69: 57 | C69: 8D
A70: 58 | B70: Sourav Mahanty | C70: 8E | D70: 3 | E70: 9681429435 | F70: 1200 | G70: 45792 | H70: 1200 | I70: 45823 | J70: 1300 | L70: 1300 | M70: 45884 | N70: 1300 | O70: 45915 | P70: 1300 | Q70: 45945 | R70: 1500 | T70: 1500 | V70: 1500 | X70: 1500 | Z70: 1500 | AB70: 1500 | AD70: 1500 | AF70: 1500
A71: 59 | B71: Mantu Das | C71: 8F | D71: 3 | E71: 7908970236 | F71: 1200 | G71: 45792 | H71: 1200 | I71: 45823 | J71: 1300 | L71: 1300 | M71: 45884 | N71: 1300 | O71: 45915 | P71: 1300 | Q71: 45945 | R71: 1500 | T71: 1500 | V71: 1500 | X71: 1500 | Z71: 1500 | AB71: 1500 | AD71: 1500 | AF71: 1500
A72: 60 | B72: Utpal Badyakar | C72: 8G | D72: 2 | E72: 9046420491 | F72: 1200 | G72: 45792 | H72: 1200 | I72: 45823 | J72: 1000 | L72: 1000 | M72: 45884 | N72: 1000 | O72: 45915 | P72: 1000 | Q72: 45945 | R72: 1200 | T72: 1200 | V72: 1200 | X72: 1200 | Z72: 1200 | AB72: 1200 | AD72: 1200 | AF72: 1200
A73: 61 | C73: 8H
A74: 62 | B74: Mintu Sk | R74: 4400 | S74: 45940
A75: 63 | B75: Omprakash
A76: 64 | B76: Shanti Da Grill | R76: 6000 | S76: 45940 | V76: 4000
B77: Total
A78: All Total | F78: =SUM(F6:F77) -> 55200 | H78: =SUM(H6:H77) -> 55200 | J78: =SUM(J6:J77) -> 54100 | L78: =SUM(L6:L77) -> 71300 | N78: =SUM(N6:N77) -> 57700 | P78: =SUM(P6:P77) -> 57700 | R78: =SUM(R6:R77) -> 78900 | T78: =SUM(T6:T77) -> 68500 | V78: =SUM(V6:V77) -> 71000 | X78: =SUM(X6:X77) -> 65800 | Z78: =SUM(Z6:Z77) -> 66000 | AA78: =SUM(AA6:AA77) -> 0 | AB78: =SUM(AB6:AB77) -> 66000 | AC78: =SUM(AC6:AC77) -> 0 | AD78: =SUM(AD6:AD77) -> 66000 | AE78: =SUM(AE6:AE77) -> 0 | AF78: =SUM(AF6:AF77) -> 64800 | AG78: =SUM(AG6:AG77) -> 0 | AH78: =SUM(AH6:AH77) -> 0
F80: 45748 | H80: 45778 | J80: 45809 | L80: 45839 | N80: 45870 | P80: 45901 | R80: 45931 | T80: 45962 | V80: 45992 | X80: 46023 | Z80: 46054 | AB80: 46082 | AD80: 46113 | AF80: 46143
A81: ALL Months received Amount | F81: =SUM(F78:AC78) -> 767400

Sheet Month wise MC
A1: Collection of Maintainance Charge (Tower-II) (Month wise)-2025/26
A3: Sl No. | B3: Month | C3: Amount
A4: 1 | B4: 45748 | C4: ='Details MC '!F78 -> 55200
A5: 2 | B5: 45778 | C5: ='Details MC '!H78 -> 55200
A6: 3 | B6: 45809 | C6: ='Details MC '!J78 -> 54100
A7: 4 | B7: 45839 | C7: ='Details MC '!L78 -> 71300
A8: 5 | B8: 45870 | C8: ='Details MC '!N78 -> 57700
A9: 6 | B9: 45901 | C9: ='Details MC '!P78 -> 57700
A10: 7 | B10: 45931 | C10: ='Details MC '!R78 -> 78900 | D10: 2BHK Rs. 1200 & 3 BHK Rs.1500 w.e.f 0ctober 2025
A11: 8 | B11: 45962 | C11: ='Details MC '!T78 -> 68500
A12: 9 | B12: 45992 | C12: ='Details MC '!V78 -> 71000
A13: 10 | B13: 46023 | C13: ='Details MC '!X78 -> 65800
A14: 11 | B14: 46054 | C14: ='Details MC '!Z78 -> 66000
A15: 12 | B15: 46082 | C15: ='Details MC '!AB78 -> 66000
A16: 13 | B16: 46113 | C16: ='Details MC '!AD78 -> 66000
A17: 14 | B17: 46143 | C17: ='Details MC '!AF78 -> 64800

Sheet EXPENSES
A1: EXPENSES APRIL'2025 TO AUGUST '2025 (Block - 2)
A2: Sr. No. | B2: Description | C2: April'25 | E2: May'25 | H2: June'25 | K2: July'25 | N2: August'25 | R2: September'25 | V2: October'25 | Z2: November'25 | AD2: December'25 | AH2: JANUARY'26 | AL2: February'26 | AP2: March'26 | AT2: April'26 | AX2: May'26
C3: Amount | D3: Dt of Payment | E3: Amount | F3: Dt of Payment | G3: Voucher No | H3: Amount | I3: Dt of Payment | J3: Remarks | K3: Amount | L3: Dt of Payment | M3: Voucher No | N3: Amount | O3: Dt of Payment | P3: Voucher No | Q3: Remarks | R3: Amount | S3: Dt of Payment | T3: Voucher No | U3: Remarks | V3: Amount | W3: Dt of Payment | X3: Voucher No | Y3: Remarks | Z3: Amount | AA3: Dt of Payment | AB3: Voucher No | AC3: Remarks | AD3: Amount | AE3: Dt of Payment | AF3: Voucher No | AG3: Remarks | AH3: Amount | AI3: Dt of Payment | AJ3: Voucher No | AK3: Remarks | AL3: Amount | AM3: Dt of Payment | AN3: Voucher No | AO3: Remarks | AP3: Amount | AQ3: Dt of Payment | AR3: Voucher No | AS3: Remarks | AT3: Amount | AU3: Dt of Payment | AV3: Voucher No | AW3: Remarks | AX3: Amount | AY3: Dt of Payment | AZ3: Voucher No | BA3: Remarks
A4: 1 | B4: Cleaning Charges of Floors within Building (House Keeping) Paid on | K4: 5500 | L4: 45843 | N4: 5500 | O4: 45874 | R4: 5500 | S4: 45905 | V4: 4950 | W4: 45938 | Z4: 5340 | AA4: 7.11.25 | AC4: UPI | AD4: 5500 | AE4: 13.12.25 | AH4: 5323 | AI4: 11.1.26 | AL4: 8430 | AM4: 46063 | AP4: 10180 | AQ4: 46100 | AT4: 11000 | AU4: 46130 | AX4: 10267 | AY4: 46157
A5: 2 | B5: Security Guard 2 Person | K5: 5000 | L5: 45843 | N5: 10000 | O5: 45874 | R5: 9190 | S5: 45905 | V5: 9300 | W5: 45938 | Z5: 10000 | AA5: 7.11.25 | AD5: 15000 | AE5: 10.12.25 | AG5: 1 security join from November | AH5: 15000 | AI5: 11.1.26 | AL5: 15000 | AM5: 46063 | AO5: 3 security guards | AP5: 15000 | AQ5: 46100 | AS5: 3 Persons | AT5: 15000 | AU5: 46130 | AX5: 15000 | AY5: 46157
A6: 3 | B6: Cleaning Charges of VAT by takening form Residency to nearest Municipality Vat paid on | H6: 1500 | I6: 45810 | K6: 1500 | L6: 45842 | N6: 1500 | O6: 45872 | R6: 1500 | S6: 45903 | V6: 1500 | W6: 45931 | Z6: 2000 | AA6: 5.11.25 | AD6: 2000 | AE6: 5.12.25 | AH6: 2000 | AI6: 46025 | AL6: 2000 | AM6: 46055 | AP6: 2500 | AQ6: 46082 | AS6: advance 500 | AT6: =1500+1000 -> 2500 | AU6: 46113 | AW6: 1500 for vat cleaning and 1000 for drain . | AX6: 3000 | AY6: 46146 | BA6: 1000 paid as advance on 14/5
A7: 4 | B7: WBSEDCL Electric Bill | E7: 15940 | F7: 45790 | H7: =18393+226 -> 18619 | I7: 45817 | J7: Rs 226/- paid to Gabinda due to off line payment during June'25 | K7: 12293 | L7: 45847 | N7: 10010 | O7: 45871 | R7: 20526 | S7: 45902 | V7: 19242 | W7: 45936 | Z7: 15366 | AA7: 7.11.25 | AD7: 22913 | AE7: 17.12.25 | AH7: 18237 | AI7: 46048 | AL7: 15635 | AM7: 46069 | AP7: 17286 | AQ7: 46082 | AT7: 12248 | AU7: 46132 | AX7: 19906 | AY7: 46154
A8: 5 | B8: Diesel for Digi Set with carriage on | E8: 5000 | F8: 45796 | K8: 4570 | L8: 45843 | R8: 5731 | S8: 45903 | AD8: =1800+5194 -> 6994 | AE8: 9.12.25 11.12.25 | AG8: 1800 paid on 9.12.25 5194 paid om 11.12.25 | AH8: 15574 | AI8: 46035 | AK8: DG Service charge | AP8: 7384 | AQ8: 46091 | AS8: 80 Ltr Disel
A9: 6 | B9: Miscellaneous Consumables & Equipments for cleaning purpose | E9: 2593 | F9: 45808 | K9: 223 | L9: 45857 | N9: 155 | O9: 45882 | R9: 140 | S9: 45908 | U9: 2 pcs Jharu | V9: 540 | W9: 45937 | Y9: Nemyle | AD9: =1716+565 -> 2281 | AE9: 16.12.25 3.12.25 | AG9: 2 time purchase Nemyle | AH9: 1128 | AI9: 46053 | AP9: =496+523 -> 1019 | AQ9: 46093 | AS9: Phnyle 10 Ltr | AT9: =100+350 -> 450 | AU9: 46103 | AW9: 2 Jharu & 1 Floor Mop | AX9: 194 | AY9: 46153 | BA9: Phnyle
Q10: Brash & Paint | R10: 936 | S10: 45925 | U10: 10 Ltr Phinile | V10: 210 | W10: 45938 | Y10: floor Mop | AD10: 55 | AE10: 6.12.25 | AG10: floor Mop | AH10: 220 | AI10: 46038 | AK10: 2 Pcs Jharu floor Mop 1pc | AL10: 405 | AM10: 46076 | AO10: 2Pcs Jharu & floor Mop 1pc
N11: 525 | O11: 45883 | Q11: Floor Cleaner | V11: 5700 | Y11: 2 nos. Neelkamal dustbin120 Ltr | AH11: 200 | AI11: 46039 | AK11: Floor cleaning Acid & others | AL11: 767 | AM11: 46075 | AO11: Floor cleaning Acid Collin
N12: 376 | O12: 45885 | Q12: 4 Ltr Phinile | AH12: 200 | AI12: 31.12.25 | AK12: Pay to Karan for cleaning
A13: 7 | B13: CCTV Camera | K13: 1349 | L13: 45852
A14: 8 | B14: Meeting purpose | H14: 1000 | I14: 45823 | N14: 50 | O14: 45879 | V14: 380 | W14: 45942 | Y14: Tea Biscuits
A15: 9 | B15: 2 Nos Iron Gate for Ground Floor | H15: 11500 | I15: 45835
A16: 10 | B16: Lock and Key | K16: 1300 | L16: 45850 | Z16: 130 | AA16: 15.11.25 | AC16: Comminuty hall
A17: 11 | B17: Stationery Items for Official Purpose | H17: 95 | I17: 45828 | K17: 650 | L17: 45850 | Z17: 60 | AA17: 15.11.25 | AC17: Xerox | AP17: =2800+650 -> 3450 | AS17: Cement Sand Labour Charge . | AT17: 3300 | AU17: 46117 | AW17: Stand Fan
A18: 12 | B18: Miscellaneous | N18: 1537 | Q18: 15 August celebration cost and common meal (533 +1004) | R18: 2000 | U18: Paid to Amaresh for Pump operating at night. | V18: 70 | W18: 45947 | Y18: Tea Biscuits | Z18: 8500 | AA18: 5.11.25 | AC18: Diwali light decoration | AD18: 1720 | AE18: 6.12.25 | AG18: 2 pcs Nilkamal chair | AL18: =21600+8400 -> 30000 | AM18: 46075 | AO18: chair& Table 24*6 | AP18: 2070 | AQ18: 46089 | AS18: Women Day celebration (pen-900+ Cadbery-1170) | AT18: =3000+1055 -> 4055 | AU18: 46113 | AW18: Plumbing meterials for 2 nos water point
A19: 13 | AL19: 680 | AM19: 46061 | AO19: Demise of Bapi's Dad | AP19: 800 | AQ19: 46096 | AS19: Satranji
A20: 14 | B20: Construction & Maintainance | AL20: =2000+800+250+960 -> 4010 | AM20: 46081 | AO20: Floor Tiles under Starecase | AP20: 2277 | AQ20: 46090 | AS20: Induction oven | AX20: =750+90+480+30+800+1500+1950 -> 5600 | BA20: 750- cement 90 white cement 480 stone chips 30 Jhali 800+1500+1950 labour charges
A21: Total | C21: =SUM(C4:C18) -> 0 | E21: =SUM(E4:E18) -> 23533 | H21: =SUM(H4:H18) -> 32714 | K21: =SUM(K4:K18) -> 32385 | N21: =SUM(N4:N18) -> 29653 | R21: =SUM(R4:R18) -> 45523 | V21: =SUM(V4:V18) -> 41892 | Z21: =SUM(Z4:Z18) -> 41396 | AD21: =SUM(AD4:AD18) -> 56463 | AH21: =SUM(AH4:AH18) -> 57882 | AL21: =SUM(AL4:AL20) -> 76927 | AP21: =SUM(AP4:AP20) -> 61966 | AT21: =SUM(AT4:AT20) -> 48553 | AX21: =SUM(AX4:AX20) -> 53967
A22: Over All | C22: =(C21+E21+H21+K21+N21+R21) -> 163808

Sheet Income and Expenses
A1: Income and Expenses Details April -25 Onwards
A3: Sl No | B3: Month | C3: Income from MC | D3: Total Income ( MC + Balance) | E3: Expenses | F3: Balance during the month
A4: 1 | B4: 45748 | C4: ='Month wise MC'!C4 -> 55200 | D4: =C4 -> 55200 | E4: =EXPENSES!C21 -> 0 | F4: =C4-E4 -> 55200
A5: 2 | B5: 45778 | C5: ='Month wise MC'!C5 -> 55200 | D5: =C5+F4 -> 110400 | E5: =EXPENSES!E21 -> 23533 | F5: =D5-E5 -> 86867
A6: 3 | B6: 45809 | C6: ='Month wise MC'!C6 -> 54100 | D6: =C6+F5 -> 140967 | E6: =EXPENSES!H21 -> 32714 | F6: =D6-E6 -> 108253
A7: 4 | B7: 45839 | C7: ='Month wise MC'!C7 -> 71300 | D7: =C7+F6 -> 179553 | E7: =EXPENSES!K21 -> 32385 | F7: =D7-E7 -> 147168
A8: 5 | B8: 45870 | C8: ='Month wise MC'!C8 -> 57700 | D8: =C8+F7 -> 204868 | E8: =EXPENSES!N21 -> 29653 | F8: =D8-E8 -> 175215
A9: 6 | B9: 45901 | C9: ='Month wise MC'!C9 -> 57700 | D9: =C9+F8 -> 232915 | E9: =EXPENSES!R21 -> 45523 | F9: =D9-E9 -> 187392
A10: 7 | B10: 45931 | C10: ='Month wise MC'!C10 -> 78900 | D10: =C10+F9 -> 266292 | E10: =EXPENSES!V21 -> 41892 | F10: =D10-E10 -> 224400
A11: 8 | B11: 45962 | C11: ='Month wise MC'!C11 -> 68500 | D11: =C11+F10 -> 292900 | E11: =EXPENSES!Z21 -> 41396 | F11: =D11-E11 -> 251504
A12: 9 | B12: 45992 | C12: ='Month wise MC'!C12 -> 71000 | D12: =C12+F11 -> 322504 | E12: =EXPENSES!AD21 -> 56463 | F12: =D12-E12 -> 266041
A13: 10 | B13: 46023 | C13: ='Month wise MC'!C13 -> 65800 | D13: =C13+F12 -> 331841 | E13: =EXPENSES!AH21 -> 57882 | F13: =D13-E13 -> 273959
A14: 11 | B14: 46054 | C14: ='Month wise MC'!C14 -> 66000 | D14: =C14+F13 -> 339959 | E14: =EXPENSES!AL21 -> 76927 | F14: =D14-E14 -> 263032
A15: 12 | B15: 46082 | C15: ='Month wise MC'!C15 -> 66000 | D15: =C15+F14 -> 329032 | E15: =EXPENSES!AP21 -> 61966 | F15: =D15-E15 -> 267066
A16: 13 | B16: 46113 | C16: ='Month wise MC'!C16 -> 66000 | D16: =C16+F15 -> 333066 | E16: =EXPENSES!AT21 -> 48553 | F16: =D16-E16 -> 284513
A17: 14 | B17: 46143 | C17: ='Month wise MC'!C17 -> 64800 | D17: =C17+F16 -> 349313 | E17: =EXPENSES!AX21 -> 53967 | F17: =D17-E17 -> 295346
A18: Total | C18: =SUM(C4:C13) -> 635400 | D18: =SUM(D4:D17) -> 3488810 | E18: =SUM(E4:E17) -> 602854
